setup.py
aleparser/__init__.py
aleparser.egg-info/PKG-INFO
aleparser.egg-info/SOURCES.txt
aleparser.egg-info/dependency_links.txt
aleparser.egg-info/top_level.txt