Metadata-Version: 1.0
Name: aleparser
Version: 0.1.1
Summary: A simple python ALE (AvidLogExchange) parser.
Home-page: https://github.com/kloptops/ALEParser
Author: Jacob Smith
Author-email: kloptops@gmail.com
License: Public Domain
Platform: UNKNOWN
Classifier: Development Status :: 4 - Beta
Classifier: Programming Language :: Python
Classifier: Topic :: Software Development :: Libraries :: Python Modules
Classifier: Intended Audience :: Developers
Classifier: License :: Public Domain
Classifier: Operating System :: MacOS :: MacOS X
Classifier: Operating System :: POSIX :: Linux
Classifier: Operating System :: Microsoft :: Windows
